{
  "ID": "959d05d4-5a36-4108-82c1-7f1e12055453",
  "Version": "3.10.0.0",
  "Name": "InappItem",
  "Content": {
    "Content": {
      "Animation": {
        "Duration": 0,
        "Speed": 1.0,
        "Timelines": [],
        "ctype": "TimelineActionData"
      },
      "AnimationList": [],
      "ObjectData": {
        "Tag": 337,
        "Children": [
          {
            "FileData": {
              "Type": "PlistSubImage",
              "Path": "treasue.png",
              "Plist": "Popups/PopupGame/AtlasPopupGame.plist"
            },
            "BlendFunc": {
              "Src": 1,
              "Dst": 771
            },
            "AnchorPoint": {
              "ScaleX": 0.5,
              "ScaleY": 0.5
            },
            "Position": {
              "X": -429.36,
              "Y": 1.3788
            },
            "Scale": {
              "ScaleX": 1.0,
              "ScaleY": 1.0
            },
            "CColor": {},
            "IconVisible": false,
            "PrePosition": {
              "X": 0.0,
              "Y": 0.0
            },
            "PreSize": {
              "X": 0.0,
              "Y": 0.0
            },
            "LeftMargin": -469.36,
            "RightMargin": 389.36,
            "TopMargin": -34.8788,
            "BottomMargin": -32.1212,
            "Tag": 375,
            "ActionTag": -620315423,
            "Size": {
              "X": 80.0,
              "Y": 67.0
            },
            "Name": "icon",
            "ctype": "SpriteObjectData"
          },
          {
            "IsCustomSize": true,
            "FontSize": 40,
            "LabelText": "1000 Xu",
            "FontResource": {
              "Type": "Normal",
              "Path": "Fonts/arialbd.ttf",
              "Plist": ""
            },
            "VerticalAlignmentType": "VT_Center",
            "OutlineColor": {
              "G": 0,
              "B": 0
            },
            "ShadowColor": {
              "R": 110,
              "G": 110,
              "B": 110
            },
            "ShadowOffsetX": 2.0,
            "ShadowOffsetY": -2.0,
            "AnchorPoint": {
              "ScaleX": 0.5,
              "ScaleY": 0.5
            },
            "Position": {
              "X": -225.78,
              "Y": 0.0003
            },
            "Scale": {
              "ScaleX": 1.0,
              "ScaleY": 1.0
            },
            "CColor": {},
            "IconVisible": false,
            "PrePosition": {
              "X": 0.0,
              "Y": 0.0
            },
            "PreSize": {
              "X": 0.0,
              "Y": 0.0
            },
            "LeftMargin": -372.28,
            "RightMargin": 79.28,
            "TopMargin": -31.5003,
            "BottomMargin": -31.4997,
            "Tag": 470,
            "ActionTag": -1957703210,
            "Size": {
              "X": 293.0,
              "Y": 63.0
            },
            "Name": "txtXu",
            "ctype": "TextObjectData"
          },
          {
            "IsCustomSize": true,
            "FontSize": 40,
            "LabelText": "20.000 VNĐ",
            "FontResource": {
              "Type": "Normal",
              "Path": "Fonts/arialbd.ttf",
              "Plist": ""
            },
            "HorizontalAlignmentType": "HT_Center",
            "VerticalAlignmentType": "VT_Center",
            "OutlineColor": {
              "G": 0,
              "B": 0
            },
            "ShadowColor": {
              "R": 110,
              "G": 110,
              "B": 110
            },
            "ShadowOffsetX": 2.0,
            "ShadowOffsetY": -2.0,
            "AnchorPoint": {
              "ScaleX": 0.5,
              "ScaleY": 0.5
            },
            "Position": {
              "X": 328.64,
              "Y": 0.0
            },
            "Scale": {
              "ScaleX": 1.0,
              "ScaleY": 1.0
            },
            "CColor": {},
            "IconVisible": false,
            "PrePosition": {
              "X": 0.0,
              "Y": 0.0
            },
            "PreSize": {
              "X": 0.0,
              "Y": 0.0
            },
            "LeftMargin": 154.64,
            "RightMargin": -502.64,
            "TopMargin": -31.5,
            "BottomMargin": -31.5,
            "Tag": 493,
            "ActionTag": -2030255432,
            "Size": {
              "X": 348.0,
              "Y": 63.0
            },
            "Name": "txtMoney",
            "ctype": "TextObjectData"
          }
        ],
        "Size": {
          "X": 0.0,
          "Y": 0.0
        },
        "Name": "Node",
        "ctype": "SingleNodeObjectData"
      },
      "UsedResources": [
        "Fonts/arialbd.ttf",
        "Popups/PopupGame/AtlasPopupGame.plist",
        "Popups/PopupGame/AtlasPopupGame.png"
      ],
      "ctype": "GameFileData"
    }
  },
  "Type": "Node"
}